rtl/apb_interface.sv
`include "apb_pkg.sv"

interface apb_interface(
  input logic pclk,
  input logic preset_n
);
  import apb_pkg::*;
  
  apb_signals_t signals;

endinterface

team_members_work/bhavana_work/package/rtl/apb_pkg.sv
package apb_pkg;
  typedef struct packed {
    logic psel;
    logic penable;
    logic pwrite;
    logic [31:0] paddr;
    logic [31:0] pwdata;
    logic [31:0] prdata;
    logic pready;
  } apb_interface_struct_t;localparam logic [31:0] SLAVE_ADDR = 32'hA000;
endpackage

team_members_work/bhavana_work/package/rtl/apb.sv
`include "apb_pkg.sv"

// Interface definition
interface apb_interface(
  input logic pclk,
  input logic preset_n,

  output logic psel,
  output logic penable,
  output logic pwrite,
  output logic [31:0] paddr,
  output logic [31:0] pwdata,
  input logic [31:0] prdata,
  input logic pready
);
endinterface

module apb_master_slave_top (
  input logic pclk,
  input logic preset_n,

  input logic [1:0] add_i,
  input logic [31:0] external_wdata_i,
  
  output logic ready_o,
  output logic [31:0] rdata_o,
  
  // Expose psel and penable for waveform monitoring
  output logic psel_o,
  output logic penable_o
);

  // Internal signals for APB
  logic psel, penable, pwrite;
  logic [31:0] paddr, pwdata, prdata;
  logic pready;

  // Instantiate APB master
  apb_add_master u_master (
    .pclk(pclk),
    .preset_n(preset_n),
    .add_i(add_i),
    
    .psel_o(psel),
    .penable_o(penable),
    .paddr_o(paddr),
    .pwrite_o(pwrite),
    .pwdata_o(pwdata),
    .prdata_i(prdata),
    .pready_i(pready),
    .external_wdata_i(external_wdata_i)
  );

  // Instantiate APB slave
  apb_add_slave u_slave (
    .pclk(pclk),
    .preset_n(preset_n),
    .psel(psel),
    .penable(penable),
    .paddr(paddr),
    .pwrite(pwrite),
    .pwdata(pwdata),
    .prdata(prdata),
    .pready(pready)
  );

  // Outputs
  assign ready_o = pready;
  assign rdata_o = prdata;

  // For waveform monitoring
  assign psel_o = psel;
  assign penable_o = penable;

endmodule

module apb_add_master (
  input logic pclk,
  input logic preset_n,

  input logic [1:0] add_i,
  input logic [31:0] external_wdata_i,
  
  output logic psel_o,
  output logic penable_o,
  output logic [31:0] paddr_o,
  output logic pwrite_o,
  output logic [31:0] pwdata_o,
  input logic [31:0] prdata_i,
  input logic pready_i
);
  import apb_pkg::*;
  
  typedef enum logic [1:0] {ST_IDLE, ST_SETUP, ST_ACCESS} apb_state_t;

  apb_state_t state_q, nxt_state;
  logic nxt_pwrite, pwrite_q;
  logic [31:0] nxt_rdata, rdata_q;

  always_ff @(posedge pclk or negedge preset_n) begin
    if (!preset_n) begin
      state_q <= ST_IDLE;
      pwrite_q <= 0;
      rdata_q <= 32'h0;
    end else begin
      state_q <= nxt_state;
      pwrite_q <= nxt_pwrite;
      rdata_q <= nxt_rdata;
    end
  end

  always_comb begin
    nxt_pwrite = pwrite_q;
    nxt_rdata = rdata_q;
    nxt_state = state_q;

    case (state_q)
      ST_IDLE: begin
        if (add_i[0]) begin
          nxt_state = ST_SETUP;
          nxt_pwrite = add_i[1];
        end
      end
      ST_SETUP: nxt_state = ST_ACCESS;
      ST_ACCESS: begin
        if (pready_i) begin
          if (!pwrite_q) nxt_rdata = prdata_i;
          nxt_state = ST_IDLE;
        end
      end
    endcase
  end

  assign psel_o = (state_q == ST_SETUP) || (state_q == ST_ACCESS);
  assign penable_o = (state_q == ST_ACCESS);
  assign paddr_o = (penable_o) ? 32'h0000a000 : 32'h0000_0000; // Example slave address
  assign pwrite_o = pwrite_q;
  assign pwdata_o = external_wdata_i;
endmodule

module apb_add_slave (
  input logic pclk,
  input logic preset_n,
  input logic psel,
  input logic penable,
  input logic [31:0] paddr,
  input logic pwrite,
  input logic [31:0] pwdata,
  output logic [31:0] prdata,
  output logic pready
);
  import apb_pkg::*;
  
  logic [31:0] register;

  assign pready = psel && penable;

  always_ff @(posedge pclk or negedge preset_n) begin
    if (!preset_n) begin
      register <= 32'b0;
    end else if (psel && penable && pwrite && (paddr == 32'h0000_0000)) begin
      register <= pwdata;
    end
  end

  always_comb begin
    if (psel && penable && !pwrite && (paddr == 32'h0000_0000)) begin
      prdata = register;
    end else begin
      prdata = 32'b0;
    end
  end
endmodule

team_members_work/bhavana_work/package/rtl/tb_apb.sv
`include "apb_pkg.sv"           // Include the package
//`include "apb_interface.sv"     // Include the interface

module tb_apb;
  logic pclk, preset_n;
  logic [1:0] add_i;
  logic [31:0] external_wdata_i;
  logic ready_o;
  logic [31:0] rdata_o;
  logic psel_o, penable_o;

  // Instantiate the DUT
  apb_master_slave_top uut (
    .pclk(pclk),
    .preset_n(preset_n),
    .add_i(add_i),
    .external_wdata_i(external_wdata_i),
    .ready_o(ready_o),
    .rdata_o(rdata_o),
    .psel_o(psel_o),
    .penable_o(penable_o)
  );

  always #10 pclk = ~pclk;

  task reset_system();
    begin
      preset_n = 0;
      add_i = 2'b00;
      external_wdata_i = 32'h0;
      @(negedge pclk);
      preset_n = 1;
      @(negedge pclk);
    end
  endtask

  task perform_write(input logic [31:0] data);
    begin
      external_wdata_i = data;
      add_i = 2'b11;
      @(posedge pclk);
      wait (ready_o); // Wait for slave to assert PREADY
      @(negedge pclk);

$display("Time: %t, Write Data: 0x%08h", $time, data); // Display the data written
      add_i = 2'b00;  // Go back to idle after the transaction


    end
  endtask
  
  task perform_read();
    begin
      add_i = 2'b01; // Read command
      @(posedge pclk);

      wait (ready_o); // Wait for slave to assert PREADY
      @(posedge pclk); // Extra clock cycle for PRDATA to stabilize
      $display("Time: %t, Read Data: 0x%08h", $time, rdata_o); // Display the data read
      add_i = 2'b00; // Go back to idle

    end
  endtask

  initial begin
    pclk = 0;

    reset_system();

    $display("Performing WRITE operation...");
    perform_write(32'h1234abcd);

    $display("Performing READ operation...");
    perform_read();
    
    $display("Performing another READ operation...");
    perform_read();

    #30;
    reset_system();

    $display("Performing another WRITE operation...");
    perform_write(32'h5678ef01);

    $display("Performing another READ operation...");
    perform_read();
    
    $display("Performing final READ operation...");
    perform_read();

    $stop;
  end
  
  initial begin
  $dumpfile("apb.vcd");
    $dumpvars(2, tb_apb);
  end
endmodule

team_members_work/bhavana_work/package/sim/apb.vcd
$date
	Thu Dec  5 23:23:36 2024
$end
$version
	QuestaSim Version 2024.2
$end
$timescale
	1ns
$end

$scope module tb_apb $end
$var reg 1 ! pclk $end
$var reg 1 " preset_n $end
$var reg 2 # add_i [1:0] $end
$var reg 32 $ external_wdata_i [31:0] $end
$var reg 1 % ready_o $end
$var reg 32 & rdata_o [31:0] $end
$var reg 1 ' psel_o $end
$var reg 1 ( penable_o $end

$scope task reset_system $end
$upscope $end

$scope task perform_write $end
$var reg 32 ) data [31:0] $end
$upscope $end

$scope task perform_read $end
$upscope $end

$scope module uut $end
$var wire 1 * pclk $end
$var wire 1 + preset_n $end
$var wire 1 , add_i [1] $end
$var wire 1 - add_i [0] $end
$var wire 1 . external_wdata_i [31] $end
$var wire 1 / external_wdata_i [30] $end
$var wire 1 0 external_wdata_i [29] $end
$var wire 1 1 external_wdata_i [28] $end
$var wire 1 2 external_wdata_i [27] $end
$var wire 1 3 external_wdata_i [26] $end
$var wire 1 4 external_wdata_i [25] $end
$var wire 1 5 external_wdata_i [24] $end
$var wire 1 6 external_wdata_i [23] $end
$var wire 1 7 external_wdata_i [22] $end
$var wire 1 8 external_wdata_i [21] $end
$var wire 1 9 external_wdata_i [20] $end
$var wire 1 : external_wdata_i [19] $end
$var wire 1 ; external_wdata_i [18] $end
$var wire 1 < external_wdata_i [17] $end
$var wire 1 = external_wdata_i [16] $end
$var wire 1 > external_wdata_i [15] $end
$var wire 1 ? external_wdata_i [14] $end
$var wire 1 @ external_wdata_i [13] $end
$var wire 1 A external_wdata_i [12] $end
$var wire 1 B external_wdata_i [11] $end
$var wire 1 C external_wdata_i [10] $end
$var wire 1 D external_wdata_i [9] $end
$var wire 1 E external_wdata_i [8] $end
$var wire 1 F external_wdata_i [7] $end
$var wire 1 G external_wdata_i [6] $end
$var wire 1 H external_wdata_i [5] $end
$var wire 1 I external_wdata_i [4] $end
$var wire 1 J external_wdata_i [3] $end
$var wire 1 K external_wdata_i [2] $end
$var wire 1 L external_wdata_i [1] $end
$var wire 1 M external_wdata_i [0] $end
$var reg 1 N ready_o $end
$var reg 32 O rdata_o [31:0] $end
$var reg 1 P psel_o $end
$var reg 1 Q penable_o $end
$var reg 1 R psel $end
$var reg 1 S penable $end
$var reg 1 T pwrite $end
$var reg 32 U paddr [31:0] $end
$var reg 32 V pwdata [31:0] $end
$var reg 32 W prdata [31:0] $end
$var reg 1 X pready $end
$upscope $end
$upscope $end
$enddefinitions $end
#0
$dumpvars
0!
0"
b0 #
b0 $
0%
b0 &
0'
0(
0N
b0 O
0P
0Q
0R
0S
0T
b0 U
b0 V
b0 W
0X
bx )
0M
0L
0K
0J
0I
0H
0G
0F
0E
0D
0C
0B
0A
0@
0?
0>
0=
0<
0;
0:
09
08
07
06
05
04
03
02
01
00
0/
0.
0-
0,
0+
0*
$end
#10
1!
1*
#20
0!
0*
1"
1+
#30
1!
1*
#40
0!
0*
b10010001101001010101111001101 )
b10010001101001010101111001101 $
b11 #
1M
1K
1J
1G
1F
1E
1D
1B
1@
1>
1;
19
18
14
11
b10010001101001010101111001101 V
1-
1,
#50
1!
1*
1R
1T
1P
1'
#60
0!
0*
#70
1!
1*
1S
b1010000000000000 U
1Q
1(
1X
1N
1%
#80
0!
0*
b0 #
b1 #
0,
#90
1!
1*
0S
0R
0P
b0 U
0Q
0(
0'
0X
0N
0%
#100
0!
0*
#110
1!
1*
b0 #
b1 #
1R
0T
1P
1'
#120
0!
0*
#130
1!
1*
1S
b1010000000000000 U
1Q
1(
1X
1N
1%
#140
0!
0*
#150
1!
1*
b0 #
0-
0S
0R
0P
b0 U
0Q
0(
0'
0X
0N
0%
#160
0!
0*
#170
1!
1*
#180
0"
b0 $
0!
0M
0K
0J
0G
0F
0E
0D
0B
0@
0>
0;
09
08
04
01
b0 V
0+
0*
1"
1+
#190
1!
1*
#200
0!
0*
b1010110011110001110111100000001 )
b1010110011110001110111100000001 $
b11 #
1M
1E
1D
1C
1B
1@
1?
1>
1:
19
18
17
14
13
11
1/
b1010110011110001110111100000001 V
1-
1,
#210
1!
1*
1R
1T
1P
1'
#220
0!
0*
#230
1!
1*
1S
b1010000000000000 U
1Q
1(
1X
1N
1%
#240
0!
0*
b0 #
b1 #
0,
#250
1!
1*
0S
0R
0P
b0 U
0Q
0(
0'
0X
0N
0%
#260
0!
0*
#270
1!
1*
b0 #
b1 #
1R
0T
1P
1'
#280
0!
0*
#290
1!
1*
1S
b1010000000000000 U
1Q
1(
1X
1N
1%
#300
0!
0*
#310
1!
1*
b0 #
